aliyunsdkfnf/__init__.py
aliyunsdkfnf/endpoint.py
aliyunsdkfnf/request/__init__.py
aliyunsdkfnf/request/v20190315/CreateFlowRequest.py
aliyunsdkfnf/request/v20190315/CreateScheduleRequest.py
aliyunsdkfnf/request/v20190315/DeleteFlowRequest.py
aliyunsdkfnf/request/v20190315/DeleteScheduleRequest.py
aliyunsdkfnf/request/v20190315/DescribeExecutionRequest.py
aliyunsdkfnf/request/v20190315/DescribeFlowRequest.py
aliyunsdkfnf/request/v20190315/DescribeScheduleRequest.py
aliyunsdkfnf/request/v20190315/GetExecutionHistoryRequest.py
aliyunsdkfnf/request/v20190315/ListExecutionsRequest.py
aliyunsdkfnf/request/v20190315/ListFlowsRequest.py
aliyunsdkfnf/request/v20190315/ListSchedulesRequest.py
aliyunsdkfnf/request/v20190315/ReportTaskFailedRequest.py
aliyunsdkfnf/request/v20190315/ReportTaskSucceededRequest.py
aliyunsdkfnf/request/v20190315/StartExecutionRequest.py
aliyunsdkfnf/request/v20190315/StartSyncExecutionRequest.py
aliyunsdkfnf/request/v20190315/StopExecutionRequest.py
aliyunsdkfnf/request/v20190315/UpdateFlowRequest.py
aliyunsdkfnf/request/v20190315/UpdateScheduleRequest.py
aliyunsdkfnf/request/v20190315/__init__.py
aliyun_python_sdk_fnf-1.8.3.dist-info/LICENSE
aliyun_python_sdk_fnf-1.8.3.dist-info/METADATA
aliyun_python_sdk_fnf-1.8.3.dist-info/WHEEL
aliyun_python_sdk_fnf-1.8.3.dist-info/top_level.txt
aliyun_python_sdk_fnf-1.8.3.dist-info/RECORD
